{"approved": false, "country": "USA", "demandcomments": "The billing demand shall be the maximum kilowatt established by the customer for any fifteen (15) consecutive minutes during the month for which the bill is rendered, as indicated or recorded by a demand meter, but it shall not be less than 75 % of the maximum demand established at any time during the preceding 11 months.  The Cooperative may, at its option, install a KVA meter or other appropriate meter to determine KVA and base the kW requirement on 90% of the KVA requirement so metered.", "demandrateunit": "kW", "demandunits": "kW", "description": "Availability to Churches only, for all uses including lighting, air conditioning, heating and power, subject to the established rules and regulations. \r\nType of Service Single-phase and three-phase where available, at available secondary voltages.  Customer shall be responsible for providing protection from single-phasing of three-phase loads.", "eiaid": 3841, "energycomments": "adjustment - sum of Tax Expense Adjustment Rider and Power Cost Adjustment. tax expense adjustment rider not present in this calculation", "energyratestructure": [[{"adj": 0.003155, "rate": 0.09811, "unit": "kWh"}]], "energyweekdayschedule": [[0, 0, 0, 0, 0, 0, 0, 0, 0, 0, 0, 0, 0, 0, 0, 0, 0, 0, 0, 0, 0, 0, 0, 0], [0, 0, 0, 0, 0, 0, 0, 0, 0, 0, 0, 0, 0, 0, 0, 0, 0, 0, 0, 0, 0, 0, 0, 0], [0, 0, 0, 0, 0, 0, 0, 0, 0, 0, 0, 0, 0, 0, 0, 0, 0, 0, 0, 0, 0, 0, 0, 0], [0, 0, 0, 0, 0, 0, 0, 0, 0, 0, 0, 0, 0, 0, 0, 0, 0, 0, 0, 0, 0, 0, 0, 0], [0, 0, 0, 0, 0, 0, 0, 0, 0, 0, 0, 0, 0, 0, 0, 0, 0, 0, 0, 0, 0, 0, 0, 0], [0, 0, 0, 0, 0, 0, 0, 0, 0, 0, 0, 0, 0, 0, 0, 0, 0, 0, 0, 0, 0, 0, 0, 0], [0, 0, 0, 0, 0, 0, 0, 0, 0, 0, 0, 0, 0, 0, 0, 0, 0, 0, 0, 0, 0, 0, 0, 0], [0, 0, 0, 0, 0, 0, 0, 0, 0, 0, 0, 0, 0, 0, 0, 0, 0, 0, 0, 0, 0, 0, 0, 0], [0, 0, 0, 0, 0, 0, 0, 0, 0, 0, 0, 0, 0, 0, 0, 0, 0, 0, 0, 0, 0, 0, 0, 0], [0, 0, 0, 0, 0, 0, 0, 0, 0, 0, 0, 0, 0, 0, 0, 0, 0, 0, 0, 0, 0, 0, 0, 0], [0, 0, 0, 0, 0, 0, 0, 0, 0, 0, 0, 0, 0, 0, 0, 0, 0, 0, 0, 0, 0, 0, 0, 0], [0, 0, 0, 0, 0, 0, 0, 0, 0, 0, 0, 0, 0, 0, 0, 0, 0, 0, 0, 0, 0, 0, 0, 0]], "energyweekendschedule": [[0, 0, 0, 0, 0, 0, 0, 0, 0, 0, 0, 0, 0, 0, 0, 0, 0, 0, 0, 0, 0, 0, 0, 0], [0, 0, 0, 0, 0, 0, 0, 0, 0, 0, 0, 0, 0, 0, 0, 0, 0, 0, 0, 0, 0, 0, 0, 0], [0, 0, 0, 0, 0, 0, 0, 0, 0, 0, 0, 0, 0, 0, 0, 0, 0, 0, 0, 0, 0, 0, 0, 0], [0, 0, 0, 0, 0, 0, 0, 0, 0, 0, 0, 0, 0, 0, 0, 0, 0, 0, 0, 0, 0, 0, 0, 0], [0, 0, 0, 0, 0, 0, 0, 0, 0, 0, 0, 0, 0, 0, 0, 0, 0, 0, 0, 0, 0, 0, 0, 0], [0, 0, 0, 0, 0, 0, 0, 0, 0, 0, 0, 0, 0, 0, 0, 0, 0, 0, 0, 0, 0, 0, 0, 0], [0, 0, 0, 0, 0, 0, 0, 0, 0, 0, 0, 0, 0, 0, 0, 0, 0, 0, 0, 0, 0, 0, 0, 0], [0, 0, 0, 0, 0, 0, 0, 0, 0, 0, 0, 0, 0, 0, 0, 0, 0, 0, 0, 0, 0, 0, 0, 0], [0, 0, 0, 0, 0, 0, 0, 0, 0, 0, 0, 0, 0, 0, 0, 0, 0, 0, 0, 0, 0, 0, 0, 0], [0, 0, 0, 0, 0, 0, 0, 0, 0, 0, 0, 0, 0, 0, 0, 0, 0, 0, 0, 0, 0, 0, 0, 0], [0, 0, 0, 0, 0, 0, 0, 0, 0, 0, 0, 0, 0, 0, 0, 0, 0, 0, 0, 0, 0, 0, 0, 0], [0, 0, 0, 0, 0, 0, 0, 0, 0, 0, 0, 0, 0, 0, 0, 0, 0, 0, 0, 0, 0, 0, 0, 0]], "fixedchargefirstmeter": 34.394375, "fixedchargeunits": "$/month", "is_default": false, "label": "5b5663555457a3e26c26b8f9", "name": "Churches", "phasewiring": "Single and 3-Phase", "revisions": [1532366581, 1532429493], "sector": "Commercial", "servicetype": "Bundled", "source": "http://coastepa.com/wp-content/uploads/2016/07/5L-Churches-Rate-effective-February-1-2016-Accessible-w-ND-statement-July-16.pdf", "sourceparent": "http://coastepa.com/rate-schedules-2/", "startdate": 1454317200, "supersedes": "539f7515ec4f024411ed0f8f", "uri": "https://apps.openei.org/IURDB/rate/view/5b5663555457a3e26c26b8f9", "utility": "Coast Electric Power Assn", "voltagecategory": "Secondary"}